[
  {
    "name": "【VGP2023受賞】サウンドバー FUNLOGY Sound3 総合80W スピーカー テレビ用スピーカー bluetooth シアターバー テレビ用 ステレオスピーカー スマートフォン 壁掛け パソコン スマホ iPhone TV TV用 pc 2.1ch 高音質 ホームシアター",
    "price": 9980,
    "url": "https://item.rakuten.co.jp/entamefactory/fun_sound/?rafcid=wsc_i_is_1029939084293981312",
    "image": "https://thumbnail.image.rakuten.co.jp/@0_mall/entamefactory/cabinet/newlp/funlogy_sound3/slide/samune_ver2.jpg?_ex=128x128",
    "shop": "FUNLOGY 楽天市場店"
  },
  {
    "name": "【VGP2024受賞】 サウンドバー FUNLOGY Soundbar 総合100W スピーカー テレビ用スピーカー bluetooth シアターバー テレビ用 スマートフォン パソコン スマホ iPhone TV TV用 pc 高音質 ホームシアター",
    "price": 12980,
    "url": "https://item.rakuten.co.jp/entamefactory/soundbar/?rafcid=wsc_i_is_1029939084293981312",
    "image": "https://thumbnail.image.rakuten.co.jp/@0_mall/entamefactory/cabinet/newlp/funlogy_soundbar/slide/slide01_4.jpg?_ex=128x128",
    "shop": "FUNLOGY 楽天市場店"
  },
  {
    "name": "【ポイント4倍｜エントリーで】【楽天1位】PCスピーカー サウンドバー 進化版！臨場感 高音質 bluetooth スピーカー パソコン/スマホ/テレビ/ゲーム機 重低音 大音量 無線 コンパクト 自宅 アウトドア 便利 長時間 USB スピーカー bluetooth 贈り物",
    "price": 3280,
    "url": "https://item.rakuten.co.jp/wishsun/a2-speaker/?rafcid=wsc_i_is_1029939084293981312",
    "image": "https://thumbnail.image.rakuten.co.jp/@0_mall/wishsun/cabinet/07820572/imgrc0083673126.jpg?_ex=128x128",
    "shop": "WISH SUN"
  },
  {
    "name": "【ポイント4倍｜エントリーで】PC スピーカー WISH SUN【高音質 進化版】小型 大音量 サウンドバー Bluetooth5.0 テレビ／パソコン／スマホ／ゲーム機 USB有線給電 3.5mmAUX接続 コンパクト【あす楽対応】 贈り物",
    "price": 2980,
    "url": "https://item.rakuten.co.jp/wishsun/e-350bs-1/?rafcid=wsc_i_is_1029939084293981312",
    "image": "https://thumbnail.image.rakuten.co.jp/@0_mall/wishsun/cabinet/07820572/imgrc0083043802.jpg?_ex=128x128",
    "shop": "WISH SUN"
  },
  {
    "name": "【楽天1位受賞】サウンドバー スピーカー テレビ PC 高音質 高出力 50W Bluetooth サウンドーバースピーカーコンパクト ホームシアター テレビスピーカー",
    "price": 8480,
    "url": "https://item.rakuten.co.jp/sanwadirect/400-sp088/?rafcid=wsc_i_is_1029939084293981312",
    "image": "https://thumbnail.image.rakuten.co.jp/@0_mall/sanwadirect/cabinet/4/400-sp088.jpg?_ex=128x128",
    "shop": "サンワダイレクト楽天市場店"
  }
]